anydocs/__init__.py
anydocs/_base.py
anydocs/_proxy.py
anydocs/load_docx.py
anydocs/load_html.py
anydocs/load_jsonl.py
anydocs/load_markdown.py
anydocs/load_pdf.py
anydocs/load_pptx.py
anydocs/load_xlsx.py
anydocs/utils.py
anydocs-0.1.1.dist-info/METADATA
anydocs-0.1.1.dist-info/WHEEL
anydocs-0.1.1.dist-info/RECORD
