Metadata-Version: 2.1
Name: anydocs
Version: 0.1.1
Summary: 
Author: bahamondex
Author-email: oscar.bahamonde@oscarbahamonde.awsapps.com
Requires-Python: >=3.10,<4.0
Classifier: Programming Language :: Python :: 3
Classifier: Programming Language :: Python :: 3.10
Classifier: Programming Language :: Python :: 3.11
Classifier: Programming Language :: Python :: 3.12
Classifier: Programming Language :: Python :: 3.13
Requires-Dist: bs4 (>=0.0.2,<0.0.3)
Requires-Dist: cachetools (>=5.5.2,<6.0.0)
Requires-Dist: cbase64 (>=0.0.9,<0.0.10)
Requires-Dist: httpx (>=0.28.1,<0.29.0)
Requires-Dist: lxml (>=5.3.1,<6.0.0)
Requires-Dist: openpyxl (>=3.1.5,<4.0.0)
Requires-Dist: pymupdf (>=1.25.4,<2.0.0)
Requires-Dist: pypdf2 (>=3.0.1,<4.0.0)
Requires-Dist: python-docx (>=1.1.2,<2.0.0)
Requires-Dist: python-pptx (>=1.0.2,<2.0.0)
